mqtt_connector/__init__.py
mqtt_connector/connector.py
muxu_io_mqtt_connector-1.1.12.dist-info/licenses/LICENSE
muxu_io_mqtt_connector-1.1.12.dist-info/METADATA
muxu_io_mqtt_connector-1.1.12.dist-info/WHEEL
muxu_io_mqtt_connector-1.1.12.dist-info/top_level.txt
muxu_io_mqtt_connector-1.1.12.dist-info/RECORD
