Metadata-Version: 2.4
Name: muxu-io-mqtt-connector
Version: 1.1.12
Summary: A robust MQTT connector for asynchronous MQTT communication
Home-page: https://github.com/muxu-io/mqtt-connector
Author: Alex Gonzalez
Author-email: Alex Gonzalez <alex@muxu.io>
License: MIT
Project-URL: Homepage, https://github.com/muxu-io/mqtt-connector
Project-URL: Bug Tracker, https://github.com/muxu-io/mqtt-connector/issues
Project-URL: Repository, https://github.com/muxu-io/mqtt-connector
Project-URL: Changelog, https://github.com/muxu-io/mqtt-connector/blob/master/CHANGELOG.md
Classifier: Programming Language :: Python :: 3
Classifier: License :: OSI Approved :: MIT License
Classifier: Operating System :: OS Independent
Classifier: Framework :: AsyncIO
Requires-Python: >=3.7
License-File: LICENSE
Requires-Dist: paho-mqtt>=2.0.0
Requires-Dist: asyncio-mqtt>=0.12.0
Provides-Extra: dev
Requires-Dist: pytest>=7.0.0; extra == "dev"
Requires-Dist: pytest-asyncio>=0.20.0; extra == "dev"
Requires-Dist: black>=23.0.0; extra == "dev"
Requires-Dist: ruff>=0.1.0; extra == "dev"
Requires-Dist: build>=0.10.0; extra == "dev"
Requires-Dist: twine>=4.0.0; extra == "dev"
Requires-Dist: python-semantic-release>=8.0.0; extra == "dev"
Dynamic: author
Dynamic: home-page
Dynamic: license-file
Dynamic: requires-python
